check_docker/__init__.py
check_docker/check_docker.py
check_docker/check_swarm.py
check_docker-2.2.1.dist-info/entry_points.txt
check_docker-2.2.1.dist-info/LICENSE
check_docker-2.2.1.dist-info/WHEEL
check_docker-2.2.1.dist-info/METADATA
check_docker-2.2.1.dist-info/RECORD
